README.md
setup.py
unlock.py
ssh_unlocker.egg-info/PKG-INFO
ssh_unlocker.egg-info/SOURCES.txt
ssh_unlocker.egg-info/dependency_links.txt
ssh_unlocker.egg-info/entry_points.txt
ssh_unlocker.egg-info/requires.txt
ssh_unlocker.egg-info/top_level.txt
unlocker/__init__.py
unlocker/argparser.py
unlocker/client.py