Metadata-Version: 1.1
Name: ssh-unlocker
Version: 0.2
Summary: SSH unlocker for unattended unlock of LUKS encrypted LVM or root disk partition using cryptsetup
Home-page: https://github.com/ViktorStiskala/cryptsetup-ssh-unlocker
Author: Viktor Stískala
Author-email: viktor@stiskala.cz
License: MIT
Platform: UNKNOWN
Classifier: Intended Audience :: System Administrators
Classifier: Operating System :: OS Independent
Classifier: Framework :: AsyncIO
Classifier: Programming Language :: Python
Classifier: Programming Language :: Python :: 3 :: Only
Classifier: Programming Language :: Python :: 3.5
Classifier: Programming Language :: Python :: 3.6
Classifier: Topic :: Utilities
